[{
    "id":1006,
    "armylvlimit":20,
    "cost":[[1,3000000],[22017,2000]]
  },{
    "id":1011,
    "armylvlimit":20,
    "cost":[[1,3000000],[22017,2000]]
  },{
    "id":1017,
    "armylvlimit":20,
    "cost":[[1,30000],[22016,1000]]
  },{
    "id":1029,
    "armylvlimit":20,
    "cost":[[1,30000],[22016,1000]]
  },{
    "id":1032,
    "armylvlimit":20,
    "cost":[[1,30000],[22016,1000]]
  },{
    "id":1035,
    "armylvlimit":20,
    "cost":[[1,30000],[22016,1000]]
  },{
    "id":1045,
    "armylvlimit":20,
    "cost":[[1,3000000],[22017,2000]]
  },{
    "id":1051,
    "armylvlimit":20,
    "cost":[[1,3000000],[22017,2000]]
  },{
    "id":1055,
    "armylvlimit":20,
    "cost":[[1,30000],[22016,1000]]
  },{
    "id":1057,
    "armylvlimit":20,
    "cost":[[1,3000000],[22017,2000]]
  },{
    "id":1062,
    "armylvlimit":20,
    "cost":[[1,3000000],[22017,2000]]
  },{
    "id":1079,
    "armylvlimit":20,
    "cost":[[1,3000000],[22017,2000]]
  }]